madenntools/__init__.py
madenntools/cv/__init__.py
madenntools/cv/base.py
madenntools/metric/__init__.py
madenntools/metric/frame_composition.py
madenntools/metric/frame_composition_utils.py
madenntools/ml/__init__.py
madenntools/os/__init__.py
madenntools/plot/__init__.py
madenntools/plot/base.py
madenntools-0.1.4.dist-info/LICENSE
madenntools-0.1.4.dist-info/METADATA
madenntools-0.1.4.dist-info/WHEEL
madenntools-0.1.4.dist-info/top_level.txt
madenntools-0.1.4.dist-info/RECORD
